<?xml version="1.0" encoding="UTF-8"?>
<feature
      id="SoftwareFmFeatures"
      label="SoftwareFm"
      version="1.0.0"
      provider-name="SoftwareFm">

   <description url="http://www.softwareFm.com">
      This is the Eclipse plugin that provides access to SoftwareFm
   </description>

   <copyright url="http://www.example.com/copyright">
      [Enter Copyright Description here.]
   </copyright>

   <license url="http://www.example.com/license">
      [Enter License Description here.]
   </license>

   <url>
      <update label="SoftwareFm update site" url="http://178.79.180.172:8080/update"/>
   </url>

   <plugin
         id="org.softwareFm.display"
         download-size="0"
         install-size="0"
         version="0.0.0"
         unpack="false"/>

   <plugin
         id="org.softwareFm.repository"
         download-size="0"
         install-size="0"
         version="0.0.0"
         unpack="false"/>

   <plugin
         id="org.softwareFm.softwareFmImages"
         download-size="0"
         install-size="0"
         version="0.0.0"
         unpack="false"/>

   <plugin
         id="org.softwareFm.eclipse"
         download-size="0"
         install-size="0"
         version="0.0.0"
         unpack="false"/>

   <plugin
         id="org.softwareFm.allTests"
         download-size="0"
         install-size="0"
         version="0.0.0"
         unpack="false"/>

   <plugin
         id="org.softwareFm.repositoryClient"
         download-size="0"
         install-size="0"
         version="0.0.0"
         unpack="false"/>

   <plugin
         id="org.softwareFm.externals"
         download-size="0"
         install-size="0"
         version="0.0.0"
         unpack="false"/>

   <plugin
         id="org.softwareFm.configuration"
         download-size="0"
         install-size="0"
         version="0.0.0"
         unpack="false"/>

   <plugin
         id="org.softwareFm.utilities"
         download-size="0"
         install-size="0"
         version="0.0.0"
         unpack="false"/>

   <plugin
         id="org.softwareFm.jdtBinding"
         download-size="0"
         install-size="0"
         version="0.0.0"
         unpack="false"/>

   <plugin
         id="orc.softwareFm.httpClient"
         download-size="0"
         install-size="0"
         version="0.0.0"
         unpack="false"/>

   <plugin
         id="org.softwareFm.selection"
         download-size="0"
         install-size="0"
         version="0.0.0"
         unpack="false"/>

</feature>
